scikit_beam-0.0.12.dist-info/DESCRIPTION.rst
scikit_beam-0.0.12.dist-info/METADATA
scikit_beam-0.0.12.dist-info/RECORD
scikit_beam-0.0.12.dist-info/WHEEL
scikit_beam-0.0.12.dist-info/metadata.json
scikit_beam-0.0.12.dist-info/top_level.txt
skbeam/__init__.py
skbeam/_version.py
skbeam/diffraction.py
skbeam/fluorescence.py
skbeam/core/__init__.py
skbeam/core/arithmetic.py
skbeam/core/calibration.py
skbeam/core/cdi.py
skbeam/core/correlation.py
skbeam/core/dpc.py
skbeam/core/feature.py
skbeam/core/image.py
skbeam/core/mask.py
skbeam/core/recip.py
skbeam/core/roi.py
skbeam/core/speckle.py
skbeam/core/spectroscopy.py
skbeam/core/stats.py
skbeam/core/utils.py
skbeam/core/accumulators/__init__.py
skbeam/core/accumulators/binned_statistic.py
skbeam/core/accumulators/histogram.cpython-36m-darwin.so
skbeam/core/accumulators/tests/__init__.py
skbeam/core/accumulators/tests/test_binned_statistic.py
skbeam/core/accumulators/tests/test_histogram.py
skbeam/core/constants/__init__.py
skbeam/core/constants/basic.py
skbeam/core/constants/xrf.py
skbeam/core/constants/xrs.py
skbeam/core/constants/data/AtomicConstants.dat
skbeam/core/constants/tests/__init__.py
skbeam/core/constants/tests/test_api.py
skbeam/core/constants/tests/test_basic.py
skbeam/core/constants/tests/test_xrf.py
skbeam/core/constants/tests/test_xrs.py
skbeam/core/fitting/__init__.py
skbeam/core/fitting/background.py
skbeam/core/fitting/funcs.py
skbeam/core/fitting/lineshapes.py
skbeam/core/fitting/models.py
skbeam/core/fitting/xrf_model.py
skbeam/core/fitting/base/__init__.py
skbeam/core/fitting/base/parameter_data.py
skbeam/core/fitting/tests/__init__.py
skbeam/core/fitting/tests/test_background.py
skbeam/core/fitting/tests/test_lineshapes.py
skbeam/core/fitting/tests/test_xrf_fit.py
skbeam/core/tests/__init__.py
skbeam/core/tests/test_arithmetic.py
skbeam/core/tests/test_calibration.py
skbeam/core/tests/test_cdi.py
skbeam/core/tests/test_correlation.py
skbeam/core/tests/test_dpc.py
skbeam/core/tests/test_feature.py
skbeam/core/tests/test_image.py
skbeam/core/tests/test_mask.py
skbeam/core/tests/test_recip.py
skbeam/core/tests/test_roi.py
skbeam/core/tests/test_speckle.py
