Metadata-Version: 2.0
Name: scikit-beam
Version: 0.0.12
Summary: Data analysis tools for X-ray science
Home-page: http://github.com/scikit-beam/scikit-beam
Author: Brookhaven National Lab
Author-email: UNKNOWN
License: BSD
Keywords: Xray Analysis
Platform: UNKNOWN
Classifier: Development Status :: 3 - Alpha
Classifier: License :: OSI Approved :: BSD License
Classifier: Programming Language :: Python :: 2.7
Classifier: Programming Language :: Python :: 3.4
Classifier: Topic :: Scientific/Engineering :: Physics
Classifier: Topic :: Scientific/Engineering :: Chemistry
Classifier: Topic :: Software Development :: Libraries
Classifier: Intended Audience :: Science/Research
Classifier: Intended Audience :: Developers
Requires-Dist: numpy
Requires-Dist: six
